<?xml version="1.0" encoding="UTF-8" standalone="yes"?>
<profile xmlns="http://www.verapdf.org/ValidationProfile" flavour="PDFA_2_B">
    <details creator="veraPDF Consortium" created="2016-02-15T10:53:07.180+03:00">
        <name>ISO 19005-2:2011 - 6.6.4 Version and conformance level identification - PDF/A Identification Schema property corr.</name>
        <description>Property corr of the PDF/A Identification Schema shall have namespace prefix pdfaid</description>
    </details>
    <hash></hash>
    <rules>
        <rule object="PDFAIdentification">
            <id specification="ISO_19005_2" clause="6.6.4" testNumber="7"/>
            <description>Property corr of the PDF/A Identification Schema shall have namespace prefix pdfaid</description>
            <test>corrPrefix == null || corrPrefix == &quot;pdfaid&quot;</test>
            <error>
                <message>Property corr of the PDF/A Identification Schema has invalid namespace prefix %1</message>
                <arguments>
                    <argument>corrPrefix</argument>
                </arguments>
            </error>
            <references/>
        </rule>
    </rules>
    <variables/>
</profile>
